MANIFEST.in
README.md
VERSION
setup.py
mklibpy_bin/__init__.py
mklibpy_bin/colored.py
mklibpy_bin/dates.py
mklibpy_bin/ls_git.py
mklibpy_bin/pip_upgrade_all.py
mklibpy_bin.egg-info/PKG-INFO
mklibpy_bin.egg-info/SOURCES.txt
mklibpy_bin.egg-info/dependency_links.txt
mklibpy_bin.egg-info/entry_points.txt
mklibpy_bin.egg-info/requires.txt
mklibpy_bin.egg-info/top_level.txt
mklibpy_bin/upgrade_manager/__init__.py
mklibpy_bin/upgrade_manager/managers.py