Metadata-Version: 1.1
Name: mklibpy-bin
Version: 0.9.1
Summary: Command line executables for mklibpy
Home-page: https://github.com/MichaelKim0407/mklibpy
Author: Michael Kim
Author-email: mkim0407@gmail.com
License: MIT
Platform: UNKNOWN
Classifier: Development Status :: 1 - Planning
Classifier: Intended Audience :: Developers
Classifier: License :: OSI Approved :: MIT License
Classifier: Programming Language :: Python :: 3.4
Classifier: Programming Language :: Python :: 3.5
Classifier: Programming Language :: Python :: 3.6
Classifier: Topic :: Terminals
Classifier: Topic :: Utilities
